motleycrew/__init__.py
motleycrew/agents/__init__.py
motleycrew/agents/abstract_parent.py
motleycrew/agents/langchain/__init__.py
motleycrew/agents/langchain/langchain.py
motleycrew/agents/langchain/legacy_react.py
motleycrew/agents/langchain/tool_calling_react.py
motleycrew/agents/langchain/tool_calling_react_prompts.py
motleycrew/agents/llama_index/__init__.py
motleycrew/agents/llama_index/llama_index.py
motleycrew/agents/llama_index/llama_index_react.py
motleycrew/agents/mixins.py
motleycrew/agents/parent.py
motleycrew/applications/__init__.py
motleycrew/applications/customer_support/README.md
motleycrew/applications/customer_support/communication.py
motleycrew/applications/customer_support/example_issues.csv
motleycrew/applications/customer_support/issue_tree.py
motleycrew/applications/customer_support/ray_serve_app.py
motleycrew/applications/customer_support/requirements.txt
motleycrew/applications/customer_support/static/index.html
motleycrew/applications/customer_support/support_agent.py
motleycrew/applications/expenses/expenses.py
motleycrew/applications/expenses/schema_delta.py
motleycrew/applications/expenses/sql_tools.py
motleycrew/applications/faust_workflow/__init__.py
motleycrew/applications/faust_workflow/faust_workflow.py
motleycrew/applications/faust_workflow/visualize.py
motleycrew/applications/research_agent/__init__.py
motleycrew/applications/research_agent/answer_task.py
motleycrew/applications/research_agent/question.py
motleycrew/applications/research_agent/question_answerer.py
motleycrew/applications/research_agent/question_generator.py
motleycrew/applications/research_agent/question_prioritizer.py
motleycrew/applications/research_agent/question_task.py
motleycrew/common/__init__.py
motleycrew/common/aux_prompts.py
motleycrew/common/defaults.py
motleycrew/common/enums.py
motleycrew/common/exceptions.py
motleycrew/common/llms.py
motleycrew/common/logging.py
motleycrew/common/types.py
motleycrew/common/utils.py
motleycrew/crew/__init__.py
motleycrew-0.3.3.dist-info/LICENSE
motleycrew-0.3.3.dist-info/METADATA
motleycrew-0.3.3.dist-info/WHEEL
motleycrew-0.3.3.dist-info/RECORD
