Metadata-Version: 2.3
Name: motleycrew
Version: 0.3.3
Summary: A lightweight agent interaction framework.
Author: MotleyCrew
Author-email: github@motleycrew.ai
Requires-Python: >=3.10,<4.0
Classifier: Programming Language :: Python :: 3
Classifier: Programming Language :: Python :: 3.10
Classifier: Programming Language :: Python :: 3.11
Classifier: Programming Language :: Python :: 3.12
Classifier: Programming Language :: Python :: 3.13
Requires-Dist: cloudpickle (>=3.0.0,<4.0.0)
Requires-Dist: kuzu (>=0.8,<0.9)
Requires-Dist: langchain (>=0.3,<0.4)
Requires-Dist: langchain-community
Requires-Dist: langchain-experimental
Requires-Dist: langchain-openai
Requires-Dist: platformdirs (>=4.2.1,<5.0.0)
Requires-Dist: pydantic (>=2.7.1,<3.0.0)
Requires-Dist: python-dotenv (>=1.0.0,<2.0.0)
